{
  "symbol": {
    "inputSymbol": "ARE",
    "requestSymbol": "ARE",
    "displaySymbol": "$ARE"
  },
  "name": "ALEXANDRIA REAL ESTATE EQUITIES, INC.",
  "price": 43.8,
  "previousClose": 41.14,
  "dayHigh": 44.08,
  "dayLow": 41.33,
  "change": 2.6599999999999966,
  "changePercent": 6.465726786582393,
  "currency": "USD",
  "exchangeName": "NYQ",
  "marketState": "",
  "series": [
    {
      "timestamp": 1777987800,
      "close": 41.689998626708984
    },
    {
      "timestamp": 1777988100,
      "close": 41.689998626708984
    },
    {
      "timestamp": 1777988400,
      "close": 41.5
    },
    {
      "timestamp": 1777988700,
      "close": 41.492698669433594
    },
    {
      "timestamp": 1777989000,
      "close": 41.36000061035156
    },
    {
      "timestamp": 1777989300,
      "close": 41.36000061035156
    },
    {
      "timestamp": 1777989600,
      "close": 41.3849983215332
    },
    {
      "timestamp": 1777989900,
      "close": 41.470001220703125
    },
    {
      "timestamp": 1777990200,
      "close": 41.564998626708984
    },
    {
      "timestamp": 1777990500,
      "close": 41.599998474121094
    },
    {
      "timestamp": 1777990800,
      "close": 41.79499816894531
    },
    {
      "timestamp": 1777991100,
      "close": 41.75410079956055
    },
    {
      "timestamp": 1777991400,
      "close": 41.55500030517578
    },
    {
      "timestamp": 1777991700,
      "close": 41.4900016784668
    },
    {
      "timestamp": 1777992000,
      "close": 41.709999084472656
    },
    {
      "timestamp": 1777992300,
      "close": 41.755001068115234
    },
    {
      "timestamp": 1777992600,
      "close": 42.189998626708984
    },
    {
      "timestamp": 1777992900,
      "close": 42.2599983215332
    },
    {
      "timestamp": 1777993200,
      "close": 42.31999969482422
    },
    {
      "timestamp": 1777993500,
      "close": 42.310001373291016
    },
    {
      "timestamp": 1777993800,
      "close": 42.435001373291016
    },
    {
      "timestamp": 1777994100,
      "close": 42.38999938964844
    },
    {
      "timestamp": 1777994400,
      "close": 42.369998931884766
    },
    {
      "timestamp": 1777994700,
      "close": 42.380001068115234
    },
    {
      "timestamp": 1777995000,
      "close": 42.3650016784668
    },
    {
      "timestamp": 1777995300,
      "close": 42.34000015258789
    },
    {
      "timestamp": 1777995600,
      "close": 42.310001373291016
    },
    {
      "timestamp": 1777995900,
      "close": 42.314998626708984
    },
    {
      "timestamp": 1777996200,
      "close": 42.35499954223633
    },
    {
      "timestamp": 1777996500,
      "close": 42.400001525878906
    },
    {
      "timestamp": 1777996800,
      "close": 42.380001068115234
    },
    {
      "timestamp": 1777997100,
      "close": 42.41999816894531
    },
    {
      "timestamp": 1777997400,
      "close": 42.470001220703125
    },
    {
      "timestamp": 1777997700,
      "close": 42.5
    },
    {
      "timestamp": 1777998000,
      "close": 42.58100128173828
    },
    {
      "timestamp": 1777998300,
      "close": 42.66999816894531
    },
    {
      "timestamp": 1777998600,
      "close": 42.599998474121094
    },
    {
      "timestamp": 1777998900,
      "close": 42.654998779296875
    },
    {
      "timestamp": 1777999200,
      "close": 42.63999938964844
    },
    {
      "timestamp": 1777999500,
      "close": 42.65999984741211
    },
    {
      "timestamp": 1777999800,
      "close": 42.625
    },
    {
      "timestamp": 1778000100,
      "close": 42.650001525878906
    },
    {
      "timestamp": 1778000400,
      "close": 42.720001220703125
    },
    {
      "timestamp": 1778000700,
      "close": 42.66999816894531
    },
    {
      "timestamp": 1778001000,
      "close": 42.72999954223633
    },
    {
      "timestamp": 1778001300,
      "close": 42.68000030517578
    },
    {
      "timestamp": 1778001600,
      "close": 42.7400016784668
    },
    {
      "timestamp": 1778001900,
      "close": 42.88010025024414
    },
    {
      "timestamp": 1778002200,
      "close": 42.86000061035156
    },
    {
      "timestamp": 1778002500,
      "close": 42.89500045776367
    },
    {
      "timestamp": 1778002800,
      "close": 43
    },
    {
      "timestamp": 1778003100,
      "close": 43.040000915527344
    },
    {
      "timestamp": 1778003400,
      "close": 43.08000183105469
    },
    {
      "timestamp": 1778003700,
      "close": 42.97999954223633
    },
    {
      "timestamp": 1778004000,
      "close": 43.1349983215332
    },
    {
      "timestamp": 1778004300,
      "close": 43.28099822998047
    },
    {
      "timestamp": 1778004600,
      "close": 43.220001220703125
    },
    {
      "timestamp": 1778004900,
      "close": 43.25
    },
    {
      "timestamp": 1778005200,
      "close": 43.35499954223633
    },
    {
      "timestamp": 1778005500,
      "close": 43.36000061035156
    },
    {
      "timestamp": 1778005800,
      "close": 43.29999923706055
    },
    {
      "timestamp": 1778006100,
      "close": 43.349998474121094
    },
    {
      "timestamp": 1778006400,
      "close": 43.4650993347168
    },
    {
      "timestamp": 1778006700,
      "close": 43.540000915527344
    },
    {
      "timestamp": 1778007000,
      "close": 43.5099983215332
    },
    {
      "timestamp": 1778007300,
      "close": 43.560001373291016
    },
    {
      "timestamp": 1778007600,
      "close": 43.689998626708984
    },
    {
      "timestamp": 1778007900,
      "close": 43.755001068115234
    },
    {
      "timestamp": 1778008200,
      "close": 43.685001373291016
    },
    {
      "timestamp": 1778008500,
      "close": 43.79999923706055
    },
    {
      "timestamp": 1778008800,
      "close": 43.97999954223633
    },
    {
      "timestamp": 1778009100,
      "close": 43.9900016784668
    },
    {
      "timestamp": 1778009400,
      "close": 43.96500015258789
    },
    {
      "timestamp": 1778009700,
      "close": 44.005001068115234
    },
    {
      "timestamp": 1778010000,
      "close": 43.97999954223633
    },
    {
      "timestamp": 1778010300,
      "close": 43.814998626708984
    },
    {
      "timestamp": 1778010600,
      "close": 43.720001220703125
    },
    {
      "timestamp": 1778010900,
      "close": 43.810001373291016
    },
    {
      "timestamp": 1778011200,
      "close": 43.79999923706055
    }
  ],
  "news": {
    "title": "RBC Cuts Price Target on Alexandria Real Estate Equities to $50 From $60, Keeps Sector Perform Rating",
    "publisher": "MT Newswires",
    "publishedAt": "2026-05-05T11:37:16.000Z"
  },
  "generatedAt": "2026-05-06T09:36:56.384Z"
}
