{
  "symbol": {
    "inputSymbol": "BAX",
    "requestSymbol": "BAX",
    "displaySymbol": "$BAX"
  },
  "name": "BAXTER INTERNATIONAL INC.",
  "price": 19.38,
  "previousClose": 19.18,
  "dayHigh": 19.52,
  "dayLow": 18.94,
  "change": 0.1999999999999993,
  "changePercent": 1.042752867570382,
  "currency": "USD",
  "exchangeName": "NYQ",
  "marketState": "",
  "series": [
    {
      "timestamp": 1779802200,
      "close": 19.1200008392334
    },
    {
      "timestamp": 1779802500,
      "close": 19.200000762939453
    },
    {
      "timestamp": 1779802800,
      "close": 19.15999984741211
    },
    {
      "timestamp": 1779803100,
      "close": 19.040000915527344
    },
    {
      "timestamp": 1779803400,
      "close": 19
    },
    {
      "timestamp": 1779803700,
      "close": 18.959999084472656
    },
    {
      "timestamp": 1779804000,
      "close": 19.1299991607666
    },
    {
      "timestamp": 1779804300,
      "close": 19.145000457763672
    },
    {
      "timestamp": 1779804600,
      "close": 19.18000030517578
    },
    {
      "timestamp": 1779804900,
      "close": 19.149999618530273
    },
    {
      "timestamp": 1779805200,
      "close": 19.1299991607666
    },
    {
      "timestamp": 1779805500,
      "close": 19.1299991607666
    },
    {
      "timestamp": 1779805800,
      "close": 19.184999465942383
    },
    {
      "timestamp": 1779806100,
      "close": 19.204999923706055
    },
    {
      "timestamp": 1779806400,
      "close": 19.264999389648438
    },
    {
      "timestamp": 1779806700,
      "close": 19.334999084472656
    },
    {
      "timestamp": 1779807000,
      "close": 19.325000762939453
    },
    {
      "timestamp": 1779807300,
      "close": 19.329999923706055
    },
    {
      "timestamp": 1779807600,
      "close": 19.309999465942383
    },
    {
      "timestamp": 1779807900,
      "close": 19.28499984741211
    },
    {
      "timestamp": 1779808200,
      "close": 19.315000534057617
    },
    {
      "timestamp": 1779808500,
      "close": 19.415000915527344
    },
    {
      "timestamp": 1779808800,
      "close": 19.375
    },
    {
      "timestamp": 1779809100,
      "close": 19.385000228881836
    },
    {
      "timestamp": 1779809400,
      "close": 19.3799991607666
    },
    {
      "timestamp": 1779809700,
      "close": 19.354999542236328
    },
    {
      "timestamp": 1779810000,
      "close": 19.375
    },
    {
      "timestamp": 1779810300,
      "close": 19.385000228881836
    },
    {
      "timestamp": 1779810600,
      "close": 19.385000228881836
    },
    {
      "timestamp": 1779810900,
      "close": 19.395000457763672
    },
    {
      "timestamp": 1779811200,
      "close": 19.375
    },
    {
      "timestamp": 1779811500,
      "close": 19.415000915527344
    },
    {
      "timestamp": 1779811800,
      "close": 19.46500015258789
    },
    {
      "timestamp": 1779812100,
      "close": 19.4950008392334
    },
    {
      "timestamp": 1779812400,
      "close": 19.5049991607666
    },
    {
      "timestamp": 1779812700,
      "close": 19.4950008392334
    },
    {
      "timestamp": 1779813000,
      "close": 19.510000228881836
    },
    {
      "timestamp": 1779813300,
      "close": 19.485000610351562
    },
    {
      "timestamp": 1779813600,
      "close": 19.485000610351562
    },
    {
      "timestamp": 1779813900,
      "close": 19.40999984741211
    },
    {
      "timestamp": 1779814200,
      "close": 19.43000030517578
    },
    {
      "timestamp": 1779814500,
      "close": 19.415000915527344
    },
    {
      "timestamp": 1779814800,
      "close": 19.375
    },
    {
      "timestamp": 1779815100,
      "close": 19.415000915527344
    },
    {
      "timestamp": 1779815400,
      "close": 19.415000915527344
    },
    {
      "timestamp": 1779815700,
      "close": 19.385000228881836
    },
    {
      "timestamp": 1779816000,
      "close": 19.375
    },
    {
      "timestamp": 1779816300,
      "close": 19.405000686645508
    },
    {
      "timestamp": 1779816600,
      "close": 19.375
    },
    {
      "timestamp": 1779816900,
      "close": 19.385000228881836
    },
    {
      "timestamp": 1779817200,
      "close": 19.385000228881836
    },
    {
      "timestamp": 1779817500,
      "close": 19.360000610351562
    },
    {
      "timestamp": 1779817800,
      "close": 19.309999465942383
    },
    {
      "timestamp": 1779818100,
      "close": 19.329999923706055
    },
    {
      "timestamp": 1779818400,
      "close": 19.344999313354492
    },
    {
      "timestamp": 1779818700,
      "close": 19.34510040283203
    },
    {
      "timestamp": 1779819000,
      "close": 19.354999542236328
    },
    {
      "timestamp": 1779819300,
      "close": 19.395000457763672
    },
    {
      "timestamp": 1779819600,
      "close": 19.420000076293945
    },
    {
      "timestamp": 1779819900,
      "close": 19.40999984741211
    },
    {
      "timestamp": 1779820200,
      "close": 19.415000915527344
    },
    {
      "timestamp": 1779820500,
      "close": 19.405000686645508
    },
    {
      "timestamp": 1779820800,
      "close": 19.40999984741211
    },
    {
      "timestamp": 1779821100,
      "close": 19.454999923706055
    },
    {
      "timestamp": 1779821400,
      "close": 19.44499969482422
    },
    {
      "timestamp": 1779821700,
      "close": 19.44499969482422
    },
    {
      "timestamp": 1779822000,
      "close": 19.46500015258789
    },
    {
      "timestamp": 1779822300,
      "close": 19.450000762939453
    },
    {
      "timestamp": 1779822600,
      "close": 19.434999465942383
    },
    {
      "timestamp": 1779822900,
      "close": 19.440000534057617
    },
    {
      "timestamp": 1779823200,
      "close": 19.44499969482422
    },
    {
      "timestamp": 1779823500,
      "close": 19.44499969482422
    },
    {
      "timestamp": 1779823800,
      "close": 19.44499969482422
    },
    {
      "timestamp": 1779824100,
      "close": 19.415000915527344
    },
    {
      "timestamp": 1779824400,
      "close": 19.405000686645508
    },
    {
      "timestamp": 1779824700,
      "close": 19.44499969482422
    },
    {
      "timestamp": 1779825000,
      "close": 19.469999313354492
    },
    {
      "timestamp": 1779825300,
      "close": 19.385000228881836
    },
    {
      "timestamp": 1779825600,
      "close": 19.3799991607666
    }
  ],
  "news": {
    "title": "Has Baxter International (BAX) Overreacted After Recent 10.9% Weekly Share Price Jump",
    "publisher": "Simply Wall St.",
    "publishedAt": "2026-05-24T06:11:14.000Z"
  },
  "generatedAt": "2026-05-27T08:49:07.969Z"
}
