{
  "symbol": {
    "inputSymbol": "BXP",
    "requestSymbol": "BXP",
    "displaySymbol": "$BXP"
  },
  "name": "BXP, INC.",
  "price": 59.9,
  "previousClose": 58.67,
  "dayHigh": 60.105,
  "dayLow": 58.32,
  "change": 1.2299999999999969,
  "changePercent": 2.096471791375485,
  "currency": "USD",
  "exchangeName": "NYQ",
  "marketState": "",
  "series": [],
  "news": {
    "title": "BXP: What does Argus have to say about BXP?",
    "publisher": "Argus Research",
    "publishedAt": "2026-05-20T00:00:00.000Z"
  },
  "generatedAt": "2026-05-21T13:32:38.191Z"
}
