{
  "symbol": {
    "inputSymbol": "CSGP",
    "requestSymbol": "CSGP",
    "displaySymbol": "$CSGP"
  },
  "name": "COSTAR GROUP, INC.",
  "price": 27.69,
  "previousClose": 28.5,
  "dayHigh": 28.862,
  "dayLow": 27.48,
  "change": -0.8099999999999987,
  "changePercent": -2.8421052631578902,
  "currency": "USD",
  "exchangeName": "NMS",
  "marketState": "",
  "series": [
    {
      "timestamp": 1784727000,
      "close": 28.649999618530273
    },
    {
      "timestamp": 1784727300,
      "close": 28.3700008392334
    },
    {
      "timestamp": 1784727600,
      "close": 28.170000076293945
    },
    {
      "timestamp": 1784727900,
      "close": 27.9950008392334
    },
    {
      "timestamp": 1784728200,
      "close": 27.674999237060547
    },
    {
      "timestamp": 1784728500,
      "close": 27.690000534057617
    },
    {
      "timestamp": 1784728800,
      "close": 27.790000915527344
    },
    {
      "timestamp": 1784729100,
      "close": 27.829999923706055
    },
    {
      "timestamp": 1784729400,
      "close": 27.78499984741211
    },
    {
      "timestamp": 1784729700,
      "close": 27.6200008392334
    },
    {
      "timestamp": 1784730000,
      "close": 27.725000381469727
    },
    {
      "timestamp": 1784730300,
      "close": 27.649999618530273
    },
    {
      "timestamp": 1784730600,
      "close": 27.625
    },
    {
      "timestamp": 1784730900,
      "close": 27.52400016784668
    },
    {
      "timestamp": 1784731200,
      "close": 27.559999465942383
    },
    {
      "timestamp": 1784731500,
      "close": 27.56999969482422
    },
    {
      "timestamp": 1784731800,
      "close": 27.649999618530273
    },
    {
      "timestamp": 1784732100,
      "close": 27.719999313354492
    },
    {
      "timestamp": 1784732400,
      "close": 27.768299102783203
    },
    {
      "timestamp": 1784732700,
      "close": 27.829999923706055
    },
    {
      "timestamp": 1784733000,
      "close": 27.799999237060547
    },
    {
      "timestamp": 1784733300,
      "close": 27.850000381469727
    },
    {
      "timestamp": 1784733600,
      "close": 27.915000915527344
    },
    {
      "timestamp": 1784733900,
      "close": 27.889999389648438
    },
    {
      "timestamp": 1784734200,
      "close": 27.829999923706055
    },
    {
      "timestamp": 1784734500,
      "close": 27.950000762939453
    },
    {
      "timestamp": 1784734800,
      "close": 27.954999923706055
    },
    {
      "timestamp": 1784735100,
      "close": 27.954999923706055
    },
    {
      "timestamp": 1784735400,
      "close": 27.979999542236328
    },
    {
      "timestamp": 1784735700,
      "close": 27.969999313354492
    },
    {
      "timestamp": 1784736000,
      "close": 27.920000076293945
    },
    {
      "timestamp": 1784736300,
      "close": 27.860000610351562
    },
    {
      "timestamp": 1784736600,
      "close": 27.940000534057617
    },
    {
      "timestamp": 1784736900,
      "close": 27.905000686645508
    },
    {
      "timestamp": 1784737200,
      "close": 27.889999389648438
    },
    {
      "timestamp": 1784737500,
      "close": 27.979999542236328
    },
    {
      "timestamp": 1784737800,
      "close": 27.9950008392334
    },
    {
      "timestamp": 1784738100,
      "close": 27.969999313354492
    },
    {
      "timestamp": 1784738400,
      "close": 28.020000457763672
    },
    {
      "timestamp": 1784738700,
      "close": 28.0049991607666
    },
    {
      "timestamp": 1784739000,
      "close": 27.969999313354492
    },
    {
      "timestamp": 1784739300,
      "close": 27.9950008392334
    },
    {
      "timestamp": 1784739600,
      "close": 28.0049991607666
    },
    {
      "timestamp": 1784739900,
      "close": 28.079999923706055
    },
    {
      "timestamp": 1784740200,
      "close": 28.075000762939453
    },
    {
      "timestamp": 1784740500,
      "close": 28.101999282836914
    },
    {
      "timestamp": 1784740800,
      "close": 28.104999542236328
    },
    {
      "timestamp": 1784741100,
      "close": 28.1299991607666
    },
    {
      "timestamp": 1784741400,
      "close": 28.139999389648438
    },
    {
      "timestamp": 1784741700,
      "close": 28.15999984741211
    },
    {
      "timestamp": 1784742000,
      "close": 28.1299991607666
    },
    {
      "timestamp": 1784742300,
      "close": 28.1200008392334
    },
    {
      "timestamp": 1784742600,
      "close": 28.110000610351562
    },
    {
      "timestamp": 1784742900,
      "close": 28.069000244140625
    },
    {
      "timestamp": 1784743200,
      "close": 28.06999969482422
    },
    {
      "timestamp": 1784743500,
      "close": 28.100000381469727
    },
    {
      "timestamp": 1784743800,
      "close": 28.059999465942383
    },
    {
      "timestamp": 1784744100,
      "close": 28.094999313354492
    },
    {
      "timestamp": 1784744400,
      "close": 28.014999389648438
    },
    {
      "timestamp": 1784744700,
      "close": 28.059999465942383
    },
    {
      "timestamp": 1784745000,
      "close": 28.06999969482422
    },
    {
      "timestamp": 1784745300,
      "close": 28.06999969482422
    },
    {
      "timestamp": 1784745600,
      "close": 28.1200008392334
    },
    {
      "timestamp": 1784745900,
      "close": 28.040000915527344
    },
    {
      "timestamp": 1784746200,
      "close": 28.014999389648438
    },
    {
      "timestamp": 1784746500,
      "close": 28.030000686645508
    },
    {
      "timestamp": 1784746800,
      "close": 28.014999389648438
    },
    {
      "timestamp": 1784747100,
      "close": 28.014999389648438
    },
    {
      "timestamp": 1784747400,
      "close": 28.059999465942383
    },
    {
      "timestamp": 1784747700,
      "close": 27.989999771118164
    },
    {
      "timestamp": 1784748000,
      "close": 28.010000228881836
    },
    {
      "timestamp": 1784748300,
      "close": 27.985000610351562
    },
    {
      "timestamp": 1784748600,
      "close": 27.954999923706055
    },
    {
      "timestamp": 1784748900,
      "close": 27.8799991607666
    },
    {
      "timestamp": 1784749200,
      "close": 27.924999237060547
    },
    {
      "timestamp": 1784749500,
      "close": 27.825000762939453
    },
    {
      "timestamp": 1784749800,
      "close": 27.7549991607666
    },
    {
      "timestamp": 1784750100,
      "close": 27.690000534057617
    },
    {
      "timestamp": 1784750400,
      "close": 27.690000534057617
    }
  ],
  "news": {
    "title": "1 S&P 500 Stock with Solid Fundamentals and 2 We Ignore",
    "publisher": "StockStory",
    "publishedAt": "2026-07-22T11:18:27.000Z"
  },
  "generatedAt": "2026-07-23T06:40:13.871Z"
}
