{
  "symbol": {
    "inputSymbol": "DOC",
    "requestSymbol": "DOC",
    "displaySymbol": "$DOC"
  },
  "name": "HEALTHPEAK PROPERTIES, INC.",
  "price": 19.49,
  "previousClose": 19.2583,
  "dayHigh": 19.6899,
  "dayLow": 19.305,
  "change": 0.23170000000000002,
  "changePercent": 1.203117616819761,
  "currency": "USD",
  "exchangeName": "NYQ",
  "marketState": "",
  "series": [
    {
      "timestamp": 1779111000,
      "close": 19.469999313354492
    },
    {
      "timestamp": 1779111300,
      "close": 19.524999618530273
    },
    {
      "timestamp": 1779111600,
      "close": 19.565000534057617
    },
    {
      "timestamp": 1779111900,
      "close": 19.665000915527344
    },
    {
      "timestamp": 1779112200,
      "close": 19.635000228881836
    },
    {
      "timestamp": 1779112500,
      "close": 19.6299991607666
    },
    {
      "timestamp": 1779112800,
      "close": 19.604999542236328
    },
    {
      "timestamp": 1779113100,
      "close": 19.53499984741211
    },
    {
      "timestamp": 1779113400,
      "close": 19.405000686645508
    },
    {
      "timestamp": 1779113700,
      "close": 19.4950008392334
    },
    {
      "timestamp": 1779114000,
      "close": 19.514999389648438
    },
    {
      "timestamp": 1779114300,
      "close": 19.524999618530273
    },
    {
      "timestamp": 1779114600,
      "close": 19.475000381469727
    },
    {
      "timestamp": 1779114900,
      "close": 19.475000381469727
    },
    {
      "timestamp": 1779115200,
      "close": 19.46500015258789
    },
    {
      "timestamp": 1779115500,
      "close": 19.434999465942383
    },
    {
      "timestamp": 1779115800,
      "close": 19.3799991607666
    },
    {
      "timestamp": 1779116100,
      "close": 19.344999313354492
    },
    {
      "timestamp": 1779116400,
      "close": 19.354999542236328
    },
    {
      "timestamp": 1779116700,
      "close": 19.475000381469727
    },
    {
      "timestamp": 1779117000,
      "close": 19.415000915527344
    },
    {
      "timestamp": 1779117300,
      "close": 19.43000030517578
    },
    {
      "timestamp": 1779117600,
      "close": 19.424999237060547
    },
    {
      "timestamp": 1779117900,
      "close": 19.424999237060547
    },
    {
      "timestamp": 1779118200,
      "close": 19.45669937133789
    },
    {
      "timestamp": 1779118500,
      "close": 19.46500015258789
    },
    {
      "timestamp": 1779118800,
      "close": 19.454999923706055
    },
    {
      "timestamp": 1779119100,
      "close": 19.475000381469727
    },
    {
      "timestamp": 1779119400,
      "close": 19.475000381469727
    },
    {
      "timestamp": 1779119700,
      "close": 19.4950008392334
    },
    {
      "timestamp": 1779120000,
      "close": 19.489999771118164
    },
    {
      "timestamp": 1779120300,
      "close": 19.5049991607666
    },
    {
      "timestamp": 1779120600,
      "close": 19.5049991607666
    },
    {
      "timestamp": 1779120900,
      "close": 19.514999389648438
    },
    {
      "timestamp": 1779121200,
      "close": 19.5049991607666
    },
    {
      "timestamp": 1779121500,
      "close": 19.485000610351562
    },
    {
      "timestamp": 1779121800,
      "close": 19.4950008392334
    },
    {
      "timestamp": 1779122100,
      "close": 19.53499984741211
    },
    {
      "timestamp": 1779122400,
      "close": 19.5049991607666
    },
    {
      "timestamp": 1779122700,
      "close": 19.5049991607666
    },
    {
      "timestamp": 1779123000,
      "close": 19.5049991607666
    },
    {
      "timestamp": 1779123300,
      "close": 19.4950008392334
    },
    {
      "timestamp": 1779123600,
      "close": 19.524999618530273
    },
    {
      "timestamp": 1779123900,
      "close": 19.55500030517578
    },
    {
      "timestamp": 1779124200,
      "close": 19.514999389648438
    },
    {
      "timestamp": 1779124500,
      "close": 19.524999618530273
    },
    {
      "timestamp": 1779124800,
      "close": 19.524999618530273
    },
    {
      "timestamp": 1779125100,
      "close": 19.514999389648438
    },
    {
      "timestamp": 1779125400,
      "close": 19.524999618530273
    },
    {
      "timestamp": 1779125700,
      "close": 19.485000610351562
    },
    {
      "timestamp": 1779126000,
      "close": 19.45009994506836
    },
    {
      "timestamp": 1779126300,
      "close": 19.475000381469727
    },
    {
      "timestamp": 1779126600,
      "close": 19.43000030517578
    },
    {
      "timestamp": 1779126900,
      "close": 19.434999465942383
    },
    {
      "timestamp": 1779127200,
      "close": 19.389999389648438
    },
    {
      "timestamp": 1779127500,
      "close": 19.3799991607666
    },
    {
      "timestamp": 1779127800,
      "close": 19.360000610351562
    },
    {
      "timestamp": 1779128100,
      "close": 19.3700008392334
    },
    {
      "timestamp": 1779128400,
      "close": 19.375
    },
    {
      "timestamp": 1779128700,
      "close": 19.395000457763672
    },
    {
      "timestamp": 1779129000,
      "close": 19.385000228881836
    },
    {
      "timestamp": 1779129300,
      "close": 19.395000457763672
    },
    {
      "timestamp": 1779129600,
      "close": 19.405000686645508
    },
    {
      "timestamp": 1779129900,
      "close": 19.415000915527344
    },
    {
      "timestamp": 1779130200,
      "close": 19.415000915527344
    },
    {
      "timestamp": 1779130500,
      "close": 19.415000915527344
    },
    {
      "timestamp": 1779130800,
      "close": 19.4950008392334
    },
    {
      "timestamp": 1779131100,
      "close": 19.454999923706055
    },
    {
      "timestamp": 1779131400,
      "close": 19.46500015258789
    },
    {
      "timestamp": 1779131700,
      "close": 19.475000381469727
    },
    {
      "timestamp": 1779132000,
      "close": 19.5049991607666
    },
    {
      "timestamp": 1779132300,
      "close": 19.5049991607666
    },
    {
      "timestamp": 1779132600,
      "close": 19.469999313354492
    },
    {
      "timestamp": 1779132900,
      "close": 19.475000381469727
    },
    {
      "timestamp": 1779133200,
      "close": 19.469999313354492
    },
    {
      "timestamp": 1779133500,
      "close": 19.485000610351562
    },
    {
      "timestamp": 1779133800,
      "close": 19.524999618530273
    },
    {
      "timestamp": 1779134100,
      "close": 19.5
    },
    {
      "timestamp": 1779134400,
      "close": 19.489999771118164
    }
  ],
  "news": {
    "title": "Verizon and 4 Other Stocks With 5% Yields—and Market-Beating Returns",
    "publisher": "Barrons.com",
    "publishedAt": "2026-05-18T19:01:00.000Z"
  },
  "generatedAt": "2026-05-19T12:21:02.687Z"
}
