{
  "symbol": {
    "inputSymbol": "MTD",
    "requestSymbol": "MTD",
    "displaySymbol": "$MTD"
  },
  "name": "METTLER-TOLEDO INTERNATIONAL INC.",
  "price": 1335.09,
  "previousClose": 1316.55,
  "dayHigh": 1341.12,
  "dayLow": 1306.4,
  "change": 18.539999999999964,
  "changePercent": 1.4082260453457875,
  "currency": "USD",
  "exchangeName": "NYQ",
  "marketState": "",
  "series": [
    {
      "timestamp": 1784208600,
      "close": 1309.114990234375
    },
    {
      "timestamp": 1784208900,
      "close": 1322.06005859375
    },
    {
      "timestamp": 1784209200,
      "close": 1327.43505859375
    },
    {
      "timestamp": 1784209500,
      "close": 1325.2449951171875
    },
    {
      "timestamp": 1784209800,
      "close": 1333.8900146484375
    },
    {
      "timestamp": 1784210100,
      "close": 1333.510009765625
    },
    {
      "timestamp": 1784210400,
      "close": 1338.0150146484375
    },
    {
      "timestamp": 1784210700,
      "close": 1338.6800537109375
    },
    {
      "timestamp": 1784211000,
      "close": 1335.2149658203125
    },
    {
      "timestamp": 1784211300,
      "close": 1334.1400146484375
    },
    {
      "timestamp": 1784211600,
      "close": 1336.7900390625
    },
    {
      "timestamp": 1784211900,
      "close": 1336.0899658203125
    },
    {
      "timestamp": 1784212200,
      "close": 1329.635009765625
    },
    {
      "timestamp": 1784212500,
      "close": 1328.2099609375
    },
    {
      "timestamp": 1784212800,
      "close": 1330.0699462890625
    },
    {
      "timestamp": 1784213100,
      "close": 1330.2099609375
    },
    {
      "timestamp": 1784213400,
      "close": 1330.364990234375
    },
    {
      "timestamp": 1784213700,
      "close": 1330.3599853515625
    },
    {
      "timestamp": 1784214000,
      "close": 1328.1099853515625
    },
    {
      "timestamp": 1784214300,
      "close": 1328.1600341796875
    },
    {
      "timestamp": 1784214600,
      "close": 1328.06494140625
    },
    {
      "timestamp": 1784214900,
      "close": 1327.06005859375
    },
    {
      "timestamp": 1784215200,
      "close": 1324.8349609375
    },
    {
      "timestamp": 1784215500,
      "close": 1327.7449951171875
    },
    {
      "timestamp": 1784215800,
      "close": 1328.300048828125
    },
    {
      "timestamp": 1784216100,
      "close": 1326.56005859375
    },
    {
      "timestamp": 1784216400,
      "close": 1328.4100341796875
    },
    {
      "timestamp": 1784216700,
      "close": 1328.699951171875
    },
    {
      "timestamp": 1784217000,
      "close": 1326.885009765625
    },
    {
      "timestamp": 1784217300,
      "close": 1328.010009765625
    },
    {
      "timestamp": 1784217600,
      "close": 1326.885009765625
    },
    {
      "timestamp": 1784217900,
      "close": 1327.0400390625
    },
    {
      "timestamp": 1784218200,
      "close": 1325.81494140625
    },
    {
      "timestamp": 1784218500,
      "close": 1325.0899658203125
    },
    {
      "timestamp": 1784218800,
      "close": 1322.9549560546875
    },
    {
      "timestamp": 1784219100,
      "close": 1321.02001953125
    },
    {
      "timestamp": 1784219400,
      "close": 1322.5350341796875
    },
    {
      "timestamp": 1784219700,
      "close": 1324.969970703125
    },
    {
      "timestamp": 1784220000,
      "close": 1328.6300048828125
    },
    {
      "timestamp": 1784220300,
      "close": 1330.4100341796875
    },
    {
      "timestamp": 1784220600,
      "close": 1329.7950439453125
    },
    {
      "timestamp": 1784220900,
      "close": 1329.81005859375
    },
    {
      "timestamp": 1784221200,
      "close": 1329.800048828125
    },
    {
      "timestamp": 1784221500,
      "close": 1330.550048828125
    },
    {
      "timestamp": 1784221800,
      "close": 1329.780029296875
    },
    {
      "timestamp": 1784222100,
      "close": 1329.6199951171875
    },
    {
      "timestamp": 1784222400,
      "close": 1329.60498046875
    },
    {
      "timestamp": 1784222700,
      "close": 1328.6800537109375
    },
    {
      "timestamp": 1784223000,
      "close": 1328.510009765625
    },
    {
      "timestamp": 1784223300,
      "close": 1329.6800537109375
    },
    {
      "timestamp": 1784223600,
      "close": 1330.06005859375
    },
    {
      "timestamp": 1784223900,
      "close": 1329.3199462890625
    },
    {
      "timestamp": 1784224200,
      "close": 1328.6700439453125
    },
    {
      "timestamp": 1784224500,
      "close": 1328.6700439453125
    },
    {
      "timestamp": 1784224800,
      "close": 1329.93994140625
    },
    {
      "timestamp": 1784225100,
      "close": 1331.3499755859375
    },
    {
      "timestamp": 1784225400,
      "close": 1332.4000244140625
    },
    {
      "timestamp": 1784225700,
      "close": 1334.3499755859375
    },
    {
      "timestamp": 1784226000,
      "close": 1333.405029296875
    },
    {
      "timestamp": 1784226300,
      "close": 1332.125
    },
    {
      "timestamp": 1784226600,
      "close": 1332.5999755859375
    },
    {
      "timestamp": 1784226900,
      "close": 1332.3349609375
    },
    {
      "timestamp": 1784227200,
      "close": 1329.5074462890625
    },
    {
      "timestamp": 1784227500,
      "close": 1329.5450439453125
    },
    {
      "timestamp": 1784227800,
      "close": 1328.9150390625
    },
    {
      "timestamp": 1784228100,
      "close": 1329.77001953125
    },
    {
      "timestamp": 1784228400,
      "close": 1330.0799560546875
    },
    {
      "timestamp": 1784228700,
      "close": 1329.199951171875
    },
    {
      "timestamp": 1784229000,
      "close": 1329.0350341796875
    },
    {
      "timestamp": 1784229300,
      "close": 1328.449951171875
    },
    {
      "timestamp": 1784229600,
      "close": 1329.1400146484375
    },
    {
      "timestamp": 1784229900,
      "close": 1329.280029296875
    },
    {
      "timestamp": 1784230200,
      "close": 1329.89501953125
    },
    {
      "timestamp": 1784230500,
      "close": 1331.1800537109375
    },
    {
      "timestamp": 1784230800,
      "close": 1332.2249755859375
    },
    {
      "timestamp": 1784231100,
      "close": 1333.1700439453125
    },
    {
      "timestamp": 1784231400,
      "close": 1335.780029296875
    },
    {
      "timestamp": 1784231700,
      "close": 1334.6300048828125
    },
    {
      "timestamp": 1784232000,
      "close": 1335.0899658203125
    }
  ],
  "news": {
    "title": "Baird Adjusts Price Target on Mettler-Toledo International to $1,308 From $1,194, Maintains Neutral Rating",
    "publisher": "MT Newswires",
    "publishedAt": "2026-07-13T13:14:50.000Z"
  },
  "generatedAt": "2026-07-17T00:13:12.611Z"
}
