{
  "symbol": {
    "inputSymbol": "NTRS",
    "requestSymbol": "NTRS",
    "displaySymbol": "$NTRS"
  },
  "name": "NORTHERN TRUST CORPORATION",
  "price": 167.575,
  "previousClose": 171.74,
  "dayHigh": 172.59,
  "dayLow": 166.83,
  "change": -4.1650000000000205,
  "changePercent": -2.4251775940375104,
  "currency": "USD",
  "exchangeName": "NMS",
  "marketState": "",
  "series": [
    {
      "timestamp": 1776864600,
      "close": 170.47000122070312
    },
    {
      "timestamp": 1776864900,
      "close": 171.35000610351562
    },
    {
      "timestamp": 1776865200,
      "close": 171.47940063476562
    },
    {
      "timestamp": 1776865500,
      "close": 171.94000244140625
    },
    {
      "timestamp": 1776865800,
      "close": 171.72000122070312
    },
    {
      "timestamp": 1776866100,
      "close": 172.35000610351562
    },
    {
      "timestamp": 1776866400,
      "close": 171.84500122070312
    },
    {
      "timestamp": 1776866700,
      "close": 171.8350067138672
    },
    {
      "timestamp": 1776867000,
      "close": 170.75999450683594
    },
    {
      "timestamp": 1776867300,
      "close": 170.39999389648438
    },
    {
      "timestamp": 1776867600,
      "close": 170.49000549316406
    },
    {
      "timestamp": 1776867900,
      "close": 169.61000061035156
    },
    {
      "timestamp": 1776868200,
      "close": 169.14999389648438
    },
    {
      "timestamp": 1776868500,
      "close": 169.0399932861328
    },
    {
      "timestamp": 1776868800,
      "close": 168.21499633789062
    },
    {
      "timestamp": 1776869100,
      "close": 169.24000549316406
    },
    {
      "timestamp": 1776869400,
      "close": 168.72000122070312
    },
    {
      "timestamp": 1776869700,
      "close": 168.85499572753906
    },
    {
      "timestamp": 1776870000,
      "close": 168.13999938964844
    },
    {
      "timestamp": 1776870300,
      "close": 168.60499572753906
    },
    {
      "timestamp": 1776870600,
      "close": 168.22999572753906
    },
    {
      "timestamp": 1776870900,
      "close": 168.52999877929688
    },
    {
      "timestamp": 1776871200,
      "close": 168.89999389648438
    },
    {
      "timestamp": 1776871500,
      "close": 168.2100067138672
    },
    {
      "timestamp": 1776871800,
      "close": 168.22999572753906
    },
    {
      "timestamp": 1776872100,
      "close": 168.00999450683594
    },
    {
      "timestamp": 1776872400,
      "close": 167.94000244140625
    },
    {
      "timestamp": 1776872700,
      "close": 168.0800018310547
    },
    {
      "timestamp": 1776873000,
      "close": 167.75970458984375
    },
    {
      "timestamp": 1776873300,
      "close": 167.85499572753906
    },
    {
      "timestamp": 1776873600,
      "close": 167.98500061035156
    },
    {
      "timestamp": 1776873900,
      "close": 168.07000732421875
    },
    {
      "timestamp": 1776874200,
      "close": 167.74000549316406
    },
    {
      "timestamp": 1776874500,
      "close": 167.86000061035156
    },
    {
      "timestamp": 1776874800,
      "close": 168.02999877929688
    },
    {
      "timestamp": 1776875100,
      "close": 167.60000610351562
    },
    {
      "timestamp": 1776875400,
      "close": 167.11000061035156
    },
    {
      "timestamp": 1776875700,
      "close": 167.3800048828125
    },
    {
      "timestamp": 1776876000,
      "close": 167.07000732421875
    },
    {
      "timestamp": 1776876300,
      "close": 167.4600067138672
    },
    {
      "timestamp": 1776876600,
      "close": 167.3800048828125
    },
    {
      "timestamp": 1776876900,
      "close": 167.17999267578125
    },
    {
      "timestamp": 1776877200,
      "close": 167.63389587402344
    },
    {
      "timestamp": 1776877500,
      "close": 167.64999389648438
    },
    {
      "timestamp": 1776877800,
      "close": 167.80999755859375
    },
    {
      "timestamp": 1776878100,
      "close": 167.72000122070312
    },
    {
      "timestamp": 1776878400,
      "close": 167.57000732421875
    },
    {
      "timestamp": 1776878700,
      "close": 167.5399932861328
    },
    {
      "timestamp": 1776879000,
      "close": 167.52000427246094
    },
    {
      "timestamp": 1776879300,
      "close": 167.51499938964844
    },
    {
      "timestamp": 1776879600,
      "close": 167.74000549316406
    },
    {
      "timestamp": 1776879900,
      "close": 167.85000610351562
    },
    {
      "timestamp": 1776880200,
      "close": 167.7449951171875
    },
    {
      "timestamp": 1776880500,
      "close": 167.64999389648438
    },
    {
      "timestamp": 1776880800,
      "close": 167.77000427246094
    },
    {
      "timestamp": 1776881100,
      "close": 167.7899932861328
    },
    {
      "timestamp": 1776881400,
      "close": 167.77999877929688
    },
    {
      "timestamp": 1776881700,
      "close": 167.73500061035156
    },
    {
      "timestamp": 1776882000,
      "close": 167.72999572753906
    },
    {
      "timestamp": 1776882300,
      "close": 167.85000610351562
    },
    {
      "timestamp": 1776882600,
      "close": 167.7100067138672
    },
    {
      "timestamp": 1776882900,
      "close": 167.67999267578125
    },
    {
      "timestamp": 1776883200,
      "close": 167.92999267578125
    },
    {
      "timestamp": 1776883500,
      "close": 167.84500122070312
    },
    {
      "timestamp": 1776883800,
      "close": 167.77999877929688
    },
    {
      "timestamp": 1776884100,
      "close": 167.69000244140625
    },
    {
      "timestamp": 1776884400,
      "close": 167.66000366210938
    },
    {
      "timestamp": 1776884700,
      "close": 167.52000427246094
    },
    {
      "timestamp": 1776885000,
      "close": 167.36000061035156
    },
    {
      "timestamp": 1776885300,
      "close": 166.97999572753906
    },
    {
      "timestamp": 1776885600,
      "close": 167.47999572753906
    },
    {
      "timestamp": 1776885900,
      "close": 167.50999450683594
    },
    {
      "timestamp": 1776886200,
      "close": 167.13999938964844
    },
    {
      "timestamp": 1776886500,
      "close": 167.50999450683594
    },
    {
      "timestamp": 1776886836,
      "close": 167.5749969482422
    }
  ],
  "news": {
    "title": "Northern Trust Expands Saphyre Collaboration to Enhance Account Lifecycle Automation",
    "publisher": "MT Newswires",
    "publishedAt": "2026-04-22T15:39:02.000Z"
  },
  "generatedAt": "2026-04-22T19:40:38.694Z"
}
