{
  "symbol": {
    "inputSymbol": "PSX",
    "requestSymbol": "PSX",
    "displaySymbol": "$PSX"
  },
  "name": "PHILLIPS 66",
  "price": 178.226,
  "previousClose": 176.19,
  "dayHigh": 180.67,
  "dayLow": 175.125,
  "change": 2.0360000000000014,
  "changePercent": 1.1555706907315972,
  "currency": "USD",
  "exchangeName": "NYQ",
  "marketState": "",
  "series": [
    {
      "timestamp": 1777901400,
      "close": 175.59500122070312
    },
    {
      "timestamp": 1777901700,
      "close": 175.95339965820312
    },
    {
      "timestamp": 1777902000,
      "close": 176.2487030029297
    },
    {
      "timestamp": 1777902300,
      "close": 175.5399932861328
    },
    {
      "timestamp": 1777902600,
      "close": 175.77999877929688
    },
    {
      "timestamp": 1777902900,
      "close": 176.06500244140625
    },
    {
      "timestamp": 1777903200,
      "close": 175.9600067138672
    },
    {
      "timestamp": 1777903500,
      "close": 176.72000122070312
    },
    {
      "timestamp": 1777903800,
      "close": 176.83999633789062
    },
    {
      "timestamp": 1777904100,
      "close": 176.36000061035156
    },
    {
      "timestamp": 1777904400,
      "close": 176.57000732421875
    },
    {
      "timestamp": 1777904700,
      "close": 177.2899932861328
    },
    {
      "timestamp": 1777905000,
      "close": 177.05999755859375
    },
    {
      "timestamp": 1777905300,
      "close": 177.3800048828125
    },
    {
      "timestamp": 1777905600,
      "close": 177.5050048828125
    },
    {
      "timestamp": 1777905900,
      "close": 177.5
    },
    {
      "timestamp": 1777906200,
      "close": 177.58999633789062
    },
    {
      "timestamp": 1777906500,
      "close": 177.5
    },
    {
      "timestamp": 1777906800,
      "close": 177.25509643554688
    },
    {
      "timestamp": 1777907100,
      "close": 177.4250030517578
    },
    {
      "timestamp": 1777907400,
      "close": 177.72999572753906
    },
    {
      "timestamp": 1777907700,
      "close": 178.22000122070312
    },
    {
      "timestamp": 1777908000,
      "close": 179.05999755859375
    },
    {
      "timestamp": 1777908300,
      "close": 179.47000122070312
    },
    {
      "timestamp": 1777908600,
      "close": 179.44500732421875
    },
    {
      "timestamp": 1777908900,
      "close": 180.44000244140625
    },
    {
      "timestamp": 1777909200,
      "close": 179.3800048828125
    },
    {
      "timestamp": 1777909500,
      "close": 179.44000244140625
    },
    {
      "timestamp": 1777909800,
      "close": 178.9600067138672
    },
    {
      "timestamp": 1777910100,
      "close": 179.05999755859375
    },
    {
      "timestamp": 1777910400,
      "close": 179.05999755859375
    },
    {
      "timestamp": 1777910700,
      "close": 179.10000610351562
    },
    {
      "timestamp": 1777911000,
      "close": 179.19000244140625
    },
    {
      "timestamp": 1777911300,
      "close": 178.92999267578125
    },
    {
      "timestamp": 1777911600,
      "close": 178.58999633789062
    },
    {
      "timestamp": 1777911900,
      "close": 178.2899932861328
    },
    {
      "timestamp": 1777912200,
      "close": 178.19000244140625
    },
    {
      "timestamp": 1777912500,
      "close": 178.02499389648438
    },
    {
      "timestamp": 1777912800,
      "close": 177.77999877929688
    },
    {
      "timestamp": 1777913100,
      "close": 177.8300018310547
    },
    {
      "timestamp": 1777913400,
      "close": 177.67999267578125
    },
    {
      "timestamp": 1777913700,
      "close": 177.39999389648438
    },
    {
      "timestamp": 1777914000,
      "close": 177.5500030517578
    },
    {
      "timestamp": 1777914300,
      "close": 177.52000427246094
    },
    {
      "timestamp": 1777914600,
      "close": 177.69000244140625
    },
    {
      "timestamp": 1777914900,
      "close": 176.88999938964844
    },
    {
      "timestamp": 1777915200,
      "close": 177.0800018310547
    },
    {
      "timestamp": 1777915500,
      "close": 177.0175018310547
    },
    {
      "timestamp": 1777915800,
      "close": 177.2899932861328
    },
    {
      "timestamp": 1777916100,
      "close": 177.35000610351562
    },
    {
      "timestamp": 1777916400,
      "close": 177.22999572753906
    },
    {
      "timestamp": 1777916700,
      "close": 177.9600067138672
    },
    {
      "timestamp": 1777917000,
      "close": 178.07000732421875
    },
    {
      "timestamp": 1777917130,
      "close": 178.22610473632812
    }
  ],
  "news": {
    "title": "Phillips 66 to Host Annual Meeting of Shareholders",
    "publisher": "Business Wire",
    "publishedAt": "2026-05-04T11:00:00.000Z"
  },
  "generatedAt": "2026-05-04T17:52:29.041Z"
}
