{
  "symbol": {
    "inputSymbol": "SOLV",
    "requestSymbol": "SOLV",
    "displaySymbol": "$SOLV"
  },
  "name": "SOLVENTUM CORPORATION",
  "price": 75.82,
  "previousClose": 74.73,
  "dayHigh": 75.945,
  "dayLow": 72.742,
  "change": 1.0899999999999892,
  "changePercent": 1.458584236585025,
  "currency": "USD",
  "exchangeName": "NYQ",
  "marketState": "",
  "series": [
    {
      "timestamp": 1779283800,
      "close": 73.54000091552734
    },
    {
      "timestamp": 1779284100,
      "close": 74.62999725341797
    },
    {
      "timestamp": 1779284400,
      "close": 74.50499725341797
    },
    {
      "timestamp": 1779284700,
      "close": 74.84500122070312
    },
    {
      "timestamp": 1779285000,
      "close": 75
    },
    {
      "timestamp": 1779285300,
      "close": 74.7699966430664
    },
    {
      "timestamp": 1779285600,
      "close": 74.91999816894531
    },
    {
      "timestamp": 1779285900,
      "close": 75.06999969482422
    },
    {
      "timestamp": 1779286200,
      "close": 75.04000091552734
    },
    {
      "timestamp": 1779286500,
      "close": 75.62999725341797
    },
    {
      "timestamp": 1779286800,
      "close": 75.47000122070312
    },
    {
      "timestamp": 1779287100,
      "close": 75.26000213623047
    },
    {
      "timestamp": 1779287400,
      "close": 75.46749877929688
    },
    {
      "timestamp": 1779287700,
      "close": 75.41999816894531
    },
    {
      "timestamp": 1779288000,
      "close": 75.33499908447266
    },
    {
      "timestamp": 1779288300,
      "close": 75.02999877929688
    },
    {
      "timestamp": 1779288600,
      "close": 75.0999984741211
    },
    {
      "timestamp": 1779288900,
      "close": 75.24500274658203
    },
    {
      "timestamp": 1779289200,
      "close": 75.25499725341797
    },
    {
      "timestamp": 1779289500,
      "close": 75.19000244140625
    },
    {
      "timestamp": 1779289800,
      "close": 75.1050033569336
    },
    {
      "timestamp": 1779290100,
      "close": 75.33000183105469
    },
    {
      "timestamp": 1779290400,
      "close": 75.47000122070312
    },
    {
      "timestamp": 1779290700,
      "close": 75.54000091552734
    },
    {
      "timestamp": 1779291000,
      "close": 75.5199966430664
    },
    {
      "timestamp": 1779291300,
      "close": 75.72000122070312
    },
    {
      "timestamp": 1779291600,
      "close": 75.75
    },
    {
      "timestamp": 1779291900,
      "close": 75.75
    },
    {
      "timestamp": 1779292200,
      "close": 75.91999816894531
    },
    {
      "timestamp": 1779292500,
      "close": 75.93000030517578
    },
    {
      "timestamp": 1779292608,
      "close": 75.81999969482422
    }
  ],
  "news": {
    "title": "What Are Wall Street Analysts' Target Price for Solventum Stock?",
    "publisher": "Barchart",
    "publishedAt": "2026-05-19T05:01:18.000Z"
  },
  "generatedAt": "2026-05-20T15:57:34.755Z"
}
