{
  "symbol": {
    "inputSymbol": "TDY",
    "requestSymbol": "TDY",
    "displaySymbol": "$TDY"
  },
  "name": "TELEDYNE TECHNOLOGIES INCORPORATED",
  "price": 615.09,
  "previousClose": 602.27,
  "dayHigh": 618.69,
  "dayLow": 602.5,
  "change": 12.82000000000005,
  "changePercent": 2.1286134125890466,
  "currency": "USD",
  "exchangeName": "NYQ",
  "marketState": "",
  "series": [
    {
      "timestamp": 1780925400,
      "close": 605.635009765625
    },
    {
      "timestamp": 1780925700,
      "close": 605.5349731445312
    },
    {
      "timestamp": 1780926000,
      "close": 607.260009765625
    },
    {
      "timestamp": 1780926300,
      "close": 608.6699829101562
    },
    {
      "timestamp": 1780926600,
      "close": 609.0700073242188
    },
    {
      "timestamp": 1780926900,
      "close": 608.469970703125
    },
    {
      "timestamp": 1780927200,
      "close": 613.219970703125
    },
    {
      "timestamp": 1780927500,
      "close": 614.5549926757812
    },
    {
      "timestamp": 1780927800,
      "close": 616.469970703125
    },
    {
      "timestamp": 1780928100,
      "close": 615.9000244140625
    },
    {
      "timestamp": 1780928400,
      "close": 615.7899780273438
    },
    {
      "timestamp": 1780928700,
      "close": 618.6900024414062
    },
    {
      "timestamp": 1780929000,
      "close": 616.5900268554688
    },
    {
      "timestamp": 1780929300,
      "close": 615.4400024414062
    },
    {
      "timestamp": 1780929600,
      "close": 613.385009765625
    },
    {
      "timestamp": 1780929900,
      "close": 614.4600219726562
    },
    {
      "timestamp": 1780930200,
      "close": 615.8499755859375
    },
    {
      "timestamp": 1780930500,
      "close": 616.5399780273438
    },
    {
      "timestamp": 1780930800,
      "close": 615.8699951171875
    },
    {
      "timestamp": 1780931100,
      "close": 615.5399780273438
    },
    {
      "timestamp": 1780931400,
      "close": 614.260009765625
    },
    {
      "timestamp": 1780931700,
      "close": 613.5399780273438
    },
    {
      "timestamp": 1780932000,
      "close": 612.780029296875
    },
    {
      "timestamp": 1780932300,
      "close": 612.1300048828125
    },
    {
      "timestamp": 1780932600,
      "close": 612.5800170898438
    },
    {
      "timestamp": 1780932900,
      "close": 612.1599731445312
    },
    {
      "timestamp": 1780933200,
      "close": 612.1599731445312
    },
    {
      "timestamp": 1780933500,
      "close": 612.3049926757812
    },
    {
      "timestamp": 1780933800,
      "close": 612.6300048828125
    },
    {
      "timestamp": 1780934100,
      "close": 613.1900024414062
    },
    {
      "timestamp": 1780934400,
      "close": 613.7999877929688
    },
    {
      "timestamp": 1780934700,
      "close": 613.4500122070312
    },
    {
      "timestamp": 1780935000,
      "close": 613.469970703125
    },
    {
      "timestamp": 1780935300,
      "close": 615.0900268554688
    },
    {
      "timestamp": 1780935626,
      "close": 615.0900268554688
    }
  ],
  "news": {
    "title": "Teledyne FLIR OEM Launches Boson SX8, the First NDAA-Compliant 8 µm SXGA LWIR Thermal Camera Module",
    "publisher": "Business Wire",
    "publishedAt": "2026-06-08T15:00:00.000Z"
  },
  "generatedAt": "2026-06-08T16:22:36.904Z"
}
