{
  "symbol": {
    "inputSymbol": "TT",
    "requestSymbol": "TT",
    "displaySymbol": "$TT"
  },
  "name": "TRANE TECHNOLOGIES PLC",
  "price": 447.94,
  "previousClose": 451.3,
  "dayHigh": 451.575,
  "dayLow": 440.955,
  "change": -3.3600000000000136,
  "changePercent": -0.7445158431198788,
  "currency": "USD",
  "exchangeName": "NYQ",
  "marketState": "",
  "series": [
    {
      "timestamp": 1780320600,
      "close": 446.6050109863281
    },
    {
      "timestamp": 1780320900,
      "close": 447.1000061035156
    },
    {
      "timestamp": 1780321200,
      "close": 446.5899963378906
    },
    {
      "timestamp": 1780321500,
      "close": 448.5899963378906
    },
    {
      "timestamp": 1780321800,
      "close": 449.510009765625
    },
    {
      "timestamp": 1780322100,
      "close": 449.30999755859375
    },
    {
      "timestamp": 1780322400,
      "close": 451.57501220703125
    },
    {
      "timestamp": 1780322700,
      "close": 449.3599853515625
    },
    {
      "timestamp": 1780323000,
      "close": 447.340087890625
    },
    {
      "timestamp": 1780323300,
      "close": 447.1099853515625
    },
    {
      "timestamp": 1780323600,
      "close": 447.6600036621094
    },
    {
      "timestamp": 1780323900,
      "close": 448.739990234375
    },
    {
      "timestamp": 1780324200,
      "close": 447.3699951171875
    },
    {
      "timestamp": 1780324500,
      "close": 446.75
    },
    {
      "timestamp": 1780324800,
      "close": 445.7699890136719
    },
    {
      "timestamp": 1780325100,
      "close": 445.2200012207031
    },
    {
      "timestamp": 1780325400,
      "close": 445.64990234375
    },
    {
      "timestamp": 1780325700,
      "close": 445.0899963378906
    },
    {
      "timestamp": 1780326000,
      "close": 445.44000244140625
    },
    {
      "timestamp": 1780326300,
      "close": 446.510009765625
    },
    {
      "timestamp": 1780326600,
      "close": 446.2550048828125
    },
    {
      "timestamp": 1780326900,
      "close": 445.1600036621094
    },
    {
      "timestamp": 1780327200,
      "close": 445.32000732421875
    },
    {
      "timestamp": 1780327500,
      "close": 444.9700012207031
    },
    {
      "timestamp": 1780327800,
      "close": 446.5400085449219
    },
    {
      "timestamp": 1780328100,
      "close": 446.4200134277344
    },
    {
      "timestamp": 1780328400,
      "close": 446.1199951171875
    },
    {
      "timestamp": 1780328700,
      "close": 446.0299987792969
    },
    {
      "timestamp": 1780329000,
      "close": 446.2250061035156
    },
    {
      "timestamp": 1780329300,
      "close": 446.2349853515625
    },
    {
      "timestamp": 1780329600,
      "close": 447.1400146484375
    },
    {
      "timestamp": 1780329900,
      "close": 447.760009765625
    },
    {
      "timestamp": 1780330200,
      "close": 447.7349853515625
    },
    {
      "timestamp": 1780330500,
      "close": 447.82000732421875
    },
    {
      "timestamp": 1780330800,
      "close": 447.7049865722656
    },
    {
      "timestamp": 1780331100,
      "close": 447.7300109863281
    },
    {
      "timestamp": 1780331400,
      "close": 447.6700134277344
    },
    {
      "timestamp": 1780331700,
      "close": 447.69000244140625
    },
    {
      "timestamp": 1780332000,
      "close": 447.67999267578125
    },
    {
      "timestamp": 1780332300,
      "close": 447.7900085449219
    },
    {
      "timestamp": 1780332479,
      "close": 447.94000244140625
    }
  ],
  "news": {
    "title": "Does MOD's Q4 Strength and $4B AI Data Center Deal Make It a Buy?",
    "publisher": "Zacks",
    "publishedAt": "2026-06-01T13:26:00.000Z"
  },
  "generatedAt": "2026-06-01T16:48:04.715Z"
}
